ApkPatcher/ANSI_COLORS.py
ApkPatcher/APK_PATCHER.py
ApkPatcher/CLI.py
ApkPatcher/MODULES.py
ApkPatcher/__init__.py
ApkPatcher/Patch/AES.py
ApkPatcher/Patch/Ads_Patch.py
ApkPatcher/Patch/CERT_NSC.py
ApkPatcher/Patch/Flutter_SSL_Patch.py
ApkPatcher/Patch/Manifest_Patch.py
ApkPatcher/Patch/Package.py
ApkPatcher/Patch/Pairip_CoreX.py
ApkPatcher/Patch/Pine_Hook.py
ApkPatcher/Patch/Random_INFO.py
ApkPatcher/Patch/Smali_Patch.py
ApkPatcher/Patch/Spoof_Patch.py
ApkPatcher/Patch/TG_Patch.py
ApkPatcher/Patch/__init__.py
ApkPatcher/Utils/Anti_Splits.py
ApkPatcher/Utils/CRC.py
ApkPatcher/Utils/Credits.py
ApkPatcher/Utils/Decompile_Compile.py
ApkPatcher/Utils/Files_Check.py
ApkPatcher/Utils/Scan.py
ApkPatcher/Utils/__init__.py
ApkPatcher/Utils/Files/AES.smali
ApkPatcher/Utils/Files/Hook.smali
ApkPatcher/Utils/Files/__init__.py
ApkPatcher/Utils/Files/lib_Pairip_CoreX.so
ApkPatcher/Utils/Pine/__init__.py
ApkPatcher/Utils/Pine/config.json
ApkPatcher/Utils/Pine/libpine32
ApkPatcher/Utils/Pine/libpine64
ApkPatcher/Utils/Pine/loader.dex
apkpatcherx-0.4.dist-info/licenses/LICENSE
apkpatcherx-0.4.dist-info/METADATA
apkpatcherx-0.4.dist-info/WHEEL
apkpatcherx-0.4.dist-info/entry_points.txt
apkpatcherx-0.4.dist-info/top_level.txt
apkpatcherx-0.4.dist-info/RECORD
